jupytercad_freecad/__init__.py
jupytercad_freecad/_version.py
jupytercad_freecad/fcstd_ydoc.py
jupytercad_freecad/handlers.py
jupytercad_freecad/freecad/__init__.py
jupytercad_freecad/freecad/loader.py
jupytercad_freecad/freecad/tools.py
jupytercad_freecad/freecad/props/__init__.py
jupytercad_freecad/freecad/props/base_prop.py
jupytercad_freecad/freecad/props/property_angle.py
jupytercad_freecad/freecad/props/property_bool.py
jupytercad_freecad/freecad/props/property_distance.py
jupytercad_freecad/freecad/props/property_geometrylist.py
jupytercad_freecad/freecad/props/property_length.py
jupytercad_freecad/freecad/props/property_link.py
jupytercad_freecad/freecad/props/property_link_list.py
jupytercad_freecad/freecad/props/property_map.py
jupytercad_freecad/freecad/props/property_partshape.py
jupytercad_freecad/freecad/props/property_placement.py
jupytercad_freecad/freecad/props/geometry/__init__.py
jupytercad_freecad/freecad/props/geometry/geom_circle.py
jupytercad_freecad/freecad/props/geometry/geom_linesegment.py
jupytercad_freecad-3.1.0.data/data/etc/jupyter/jupyter_server_config.d/jupytercad_freecad.json
jupytercad_freecad-3.1.0.data/data/share/jupyter/labextensions/@jupytercad/jupytercad-freecad/package.json
jupytercad_freecad-3.1.0.data/data/share/jupyter/labextensions/@jupytercad/jupytercad-freecad/static/728.37ed8caea06dadfebc75.js
jupytercad_freecad-3.1.0.data/data/share/jupyter/labextensions/@jupytercad/jupytercad-freecad/static/844.4a6543b39b932f905125.js
jupytercad_freecad-3.1.0.data/data/share/jupyter/labextensions/@jupytercad/jupytercad-freecad/static/remoteEntry.95228b7f02587cf4aab0.js
jupytercad_freecad-3.1.0.data/data/share/jupyter/labextensions/@jupytercad/jupytercad-freecad/static/style.js
jupytercad_freecad-3.1.0.data/data/share/jupyter/labextensions/@jupytercad/jupytercad-freecad/static/third-party-licenses.json
jupytercad_freecad-3.1.0.data/data/share/jupyter/labextensions/@jupytercad/jupytercad-freecad/install.json
jupytercad_freecad-3.1.0.dist-info/METADATA
jupytercad_freecad-3.1.0.dist-info/WHEEL
jupytercad_freecad-3.1.0.dist-info/entry_points.txt
jupytercad_freecad-3.1.0.dist-info/licenses/LICENSE
jupytercad_freecad-3.1.0.dist-info/RECORD
