Metadata-Version: 2.4
Name: jupytercad_freecad
Version: 3.1.0
Dynamic: Keywords
Summary: A JupyterCAD extension for FreeCAD.
Project-URL: Homepage, https://github.com/jupytercad/JupyterCAD-FreeCAD
Project-URL: Bug Tracker, https://github.com/jupytercad/JupyterCAD-FreeCAD/issues
Project-URL: Repository, https://github.com/jupytercad/JupyterCAD-FreeCAD
Author: JupyterCad contributors
License: BSD 3-Clause License
License-File: LICENSE
Classifier: Framework :: Jupyter
Classifier: Framework :: Jupyter :: JupyterLab
Classifier: Framework :: Jupyter :: JupyterLab :: 4
Classifier: Framework :: Jupyter :: JupyterLab :: Extensions
Classifier: Framework :: Jupyter :: JupyterLab :: Extensions :: Prebuilt
Classifier: License :: OSI Approved :: BSD License
Classifier: Programming Language :: Python
Classifier: Programming Language :: Python :: 3
Classifier: Programming Language :: Python :: 3.8
Classifier: Programming Language :: Python :: 3.9
Classifier: Programming Language :: Python :: 3.10
Classifier: Programming Language :: Python :: 3.11
Classifier: Programming Language :: Python :: 3.12
Classifier: Programming Language :: Python :: 3.13
Classifier: Programming Language :: Python :: 3.14
Requires-Python: >=3.8
Requires-Dist: jupyter-ydoc<4,>=3
Requires-Dist: jupytercad-core<4,>=3.4.0
